deer/__init__.py
deer/encoder_model.py
deer/post_processing.py
deer/prompt_templates.py
deer/utils.py
deer_probe-0.1.1.dist-info/METADATA
deer_probe-0.1.1.dist-info/WHEEL
deer_probe-0.1.1.dist-info/top_level.txt
deer_probe-0.1.1.dist-info/RECORD
